periodic_table_tui/__init__.py
periodic_table_tui/__main__.py
periodic_table_tui/elements.json
periodic_table_tui/periodic_table.py
periodic_table_tui-0.1.2.dist-info/LICENSE
periodic_table_tui-0.1.2.dist-info/METADATA
periodic_table_tui-0.1.2.dist-info/WHEEL
periodic_table_tui-0.1.2.dist-info/entry_points.txt
periodic_table_tui-0.1.2.dist-info/top_level.txt
periodic_table_tui-0.1.2.dist-info/RECORD
