Metadata-Version: 2.1
Name: periodic-table-tui
Version: 0.1.2
Summary: A periodic table for the command line
Home-page: https://github.com/pryme-svg/periodic-table-tui
Author: pryme-svg
Author-email: edoc.www@gmail.com
License: GPL3
Keywords: periodic_table
Platform: UNKNOWN
Classifier: Programming Language :: Python :: 3
Classifier: License :: OSI Approved :: GNU General Public License v3 or later (GPLv3+)
Classifier: Operating System :: OS Independent
Requires-Python: >=3.6
License-File: LICENSE
